setup.py
aerospace_calculator/__init__.py
aerospace_calculator/aerospace_basics.py
aerospace_calculator.egg-info/PKG-INFO
aerospace_calculator.egg-info/SOURCES.txt
aerospace_calculator.egg-info/dependency_links.txt
aerospace_calculator.egg-info/not-zip-safe
aerospace_calculator.egg-info/top_level.txt