Metadata-Version: 1.0
Name: aerospace-calculator
Version: 0.1
Summary: Aerospace Calculator for basic and advanced calculations
Home-page: https://github.com/rfukutome/aerospace-calculator.git
Author: Richard Fukutome
Author-email: rfukutome@gmail.com
License: MIT
Platform: UNKNOWN
